gma/__init__.py
gma/const.pyd
gma/crs.pyd
gma/etools.pyd
gma/gft.pyd
gma/io.pyd
gma/rsvi.pyd
gma/_algos/__init__.py
gma/_algos/units.pyd
gma/_algos/arrmt/__init__.py
gma/_algos/arrmt/base.pyd
gma/_algos/arrmt/enhance.pyd
gma/_algos/arrmt/filter.pyd
gma/_algos/arrmt/metrics.pyd
gma/_algos/arrmt/prepro.pyd
gma/_algos/arrmt/signal.pyd
gma/_algos/climet/__init__.py
gma/_algos/climet/base.pyd
gma/_algos/climet/clindex.pyd
gma/_algos/climet/cmana.pyd
gma/_algos/climet/et0.pyd
gma/_algos/climet/meindex.pyd
gma/_algos/climet/static.pyd
gma/_algos/climet/utils.pyd
gma/_algos/core/__init__.py
gma/_algos/core/dtype.pyd
gma/_algos/core/env.pyd
gma/_algos/core/error.pyd
gma/_algos/core/gdata.pyd
gma/_algos/core/gformat.pyd
gma/_algos/core/iplib.pyd
gma/_algos/core/tools.pyd
gma/_algos/dataio/__init__.py
gma/_algos/dataio/base.pyd
gma/_algos/dataio/create.pyd
gma/_algos/dataio/database.pyd
gma/_algos/dataio/open.pyd
gma/_algos/dataio/rads.pyd
gma/_algos/dataio/spatref.pyd
gma/_algos/dataio/sql.pyd
gma/_algos/dataio/utils.pyd
gma/_algos/dataio/veds.pyd
gma/_algos/dataio/vrt.pyd
gma/_algos/dataio/warp.pyd
gma/_algos/dataio/extlib/_gdal.cp311-win_amd64.pyd
gma/_algos/dataio/extlib/_gdal_array.cp311-win_amd64.pyd
gma/_algos/dataio/extlib/_ogr.cp311-win_amd64.pyd
gma/_algos/dataio/extlib/_osr.cp311-win_amd64.pyd
gma/_algos/rsidx/__init__.py
gma/_algos/rsidx/base.pyd
gma/_algos/rsidx/norvi.pyd
gma/_algos/rsidx/recalvi.pyd
gma/_algos/spat/__init__.py
gma/_algos/spat/base.pyd
gma/_algos/spat/datum.pyd
gma/_algos/spat/default.pyd
gma/_algos/spat/exspat.pyd
gma/_algos/spat/geocrs.pyd
gma/_algos/spat/projm.pyd
gma/_algos/spmis/__init__.py
gma/_algos/spmis/base.pyd
gma/_algos/spmis/extraction.pyd
gma/_algos/spmis/interpolate.pyd
gma/_algos/spmis/meatran.pyd
gma/_algos/spmis/poly.pyd
gma/_algos/spmis/krige/__init__.py
gma/_algos/spmis/krige/core.pyd
gma/_algos/spmis/krige/variogram.pyd
gma/_data/GMA_World_DEM_GEBCO.jp2
gma/_data/GMA_World_NaturalEarth.tif
gma/_data/format.db
gma-2.2.1.dist-info/METADATA
gma-2.2.1.dist-info/WHEEL
gma-2.2.1.dist-info/top_level.txt
gma-2.2.1.dist-info/RECORD
