Metadata-Version: 2.1
Name: gma
Version: 2.2.1
Summary: Geographic and Meteorological Analysis.
Home-page: http://gma.luosgeo.com/
Author: Li Chongrui
Author-email: 858998723@qq.com
License: MIT
Platform: win_amd64
Requires-Python: >=3.10
Requires-Dist: pandas>=2.0.0
Requires-Dist: numpy>=2.0.0
Requires-Dist: scipy>=1.14.0
Requires-Dist: matplotlib>=3.8.0
